deeppavlov_agent/__init__.py
deeppavlov_agent/cmd_client.py
deeppavlov_agent/log_config.yml
deeppavlov_agent/parse_config.py
deeppavlov_agent/run.py
deeppavlov_agent/run_http.py
deeppavlov_agent/run_tg.py
deeppavlov_agent/settings.py
deeppavlov_agent/setup_agent.py
deeppavlov_agent/core/__init__.py
deeppavlov_agent/core/agent.py
deeppavlov_agent/core/connectors.py
deeppavlov_agent/core/db.py
deeppavlov_agent/core/log.py
deeppavlov_agent/core/pipeline.py
deeppavlov_agent/core/service.py
deeppavlov_agent/core/state_manager.py
deeppavlov_agent/core/state_schema.py
deeppavlov_agent/core/telegram_client.py
deeppavlov_agent/core/workflow_manager.py
deeppavlov_agent/core/transport/__init__.py
deeppavlov_agent/core/transport/base.py
deeppavlov_agent/core/transport/mapping.py
deeppavlov_agent/core/transport/messages.py
deeppavlov_agent/core/transport/settings.py
deeppavlov_agent/core/transport/gateways/__init__.py
deeppavlov_agent/core/transport/gateways/rabbitmq.py
deeppavlov_agent/http_api/__init__.py
deeppavlov_agent/http_api/api.py
deeppavlov_agent/http_api/handlers.py
deeppavlov_agent/http_api/templates/__init__.py
deeppavlov_agent/http_api/templates/base.html
deeppavlov_agent/http_api/templates/chat.html
deeppavlov_agent/http_api/templates/services_ws_highcharts.html
deeppavlov_agent/state_formatters/__init__.py
deeppavlov_agent/state_formatters/dp_formatters.py
deeppavlov_agent/state_formatters/output_formatters.py
deeppavlov_agent/tests/__init__.py
deeppavlov_agent/tests/workflow_manager_test.py
deeppavlov_agent-2.2.0.dist-info/LICENSE
deeppavlov_agent-2.2.0.dist-info/METADATA
deeppavlov_agent-2.2.0.dist-info/WHEEL
deeppavlov_agent-2.2.0.dist-info/top_level.txt
deeppavlov_agent-2.2.0.dist-info/RECORD
